gigawork/__init__.py
gigawork/__main__.py
gigawork/change_types.py
gigawork/extractors.py
gigawork/github-workflow.json
gigawork/main.py
gigawork/param_types.py
gigawork/repository.py
gigawork/utils.py
gigawork/workflow_recognition.py
gigawork-1.4.3.dist-info/licenses/LICENSE.txt
gigawork-1.4.3.dist-info/METADATA
gigawork-1.4.3.dist-info/WHEEL
gigawork-1.4.3.dist-info/entry_points.txt
gigawork-1.4.3.dist-info/top_level.txt
gigawork-1.4.3.dist-info/zip-safe
gigawork-1.4.3.dist-info/RECORD
