Metadata-Version: 2.4
Name: gigawork
Version: 1.4.3
Summary: A tool for extracting GitHub Actions workflows
Author-email: Guillaume Cardoen <Guillaume.CARDOEN@umons.ac.be>
License-Expression: LGPL-3.0-or-later
Project-URL: homepage, https://github.com/sgl-umons/gigawork
Project-URL: repository, https://github.com/sgl-umons/gigawork
Keywords: gha,workflows,dataset,tool
Classifier: Development Status :: 5 - Production/Stable
Classifier: Intended Audience :: Developers
Classifier: Intended Audience :: Education
Classifier: Intended Audience :: Information Technology
Classifier: Intended Audience :: Science/Research
Classifier: Programming Language :: Python :: 3 :: Only
Classifier: Programming Language :: Python :: 3.10
Classifier: Programming Language :: Python :: 3.11
Classifier: Programming Language :: Python :: 3.12
Classifier: Programming Language :: Python :: 3.13
Classifier: Programming Language :: Python :: 3.14
Requires-Python: >=3.10
License-File: LICENSE.txt
Requires-Dist: click~=8.1.7
Requires-Dist: GitPython~=3.1.45
Requires-Dist: jsonschema~=4.21.0
Requires-Dist: ruamel.yaml~=0.18.6
Dynamic: license-file
